troml_dev_status/__about__.py
troml_dev_status/__init__.py
troml_dev_status/__main__.py
troml_dev_status/checks.py
troml_dev_status/checks_completeness.py
troml_dev_status/cli.py
troml_dev_status/engine.py
troml_dev_status/models.py
troml_dev_status/py.typed
troml_dev_status/reporting.py
troml_dev_status/analysis/__init__.py
troml_dev_status/analysis/bureaucracy.py
troml_dev_status/analysis/filesystem.py
troml_dev_status/analysis/find_tests.py
troml_dev_status/analysis/git.py
troml_dev_status/analysis/iter_the_files.py
troml_dev_status/analysis/pypi.py
troml_dev_status/analysis/readme_eval.py
troml_dev_status/analysis/signs_of_bad.py
troml_dev_status/analysis/support_per_endoflife.py
troml_dev_status/analysis/supported_python.py
troml_dev_status/analysis/validate_changelog.py
troml_dev_status/utils/__init__.py
troml_dev_status/utils/setup_logging.py
troml_dev_status/utils/tomlkit_utils.py
troml_dev_status-0.4.2.dist-info/METADATA
troml_dev_status-0.4.2.dist-info/WHEEL
troml_dev_status-0.4.2.dist-info/entry_points.txt
troml_dev_status-0.4.2.dist-info/licenses/LICENSE
troml_dev_status-0.4.2.dist-info/RECORD
