Metadata-Version: 2.4
Name: troml-dev-status
Version: 0.4.2
Summary: Objectively infer PyPI Development Status classifiers from code and release artifacts.
Project-URL: Repository, https://github.com/matthewdeanmartin/troml_dev_status
Project-URL: Documentation, https://troml-dev-status.readthedocs.io/en/latest/
Project-URL: Changelog, https://github.com/matthewdeanmartin/troml_dev_status/blob/main/CHANGELOG.md
Project-URL: homepage, https://github.com/matthewdeanmartin/troml_dev_status
Project-URL: issues, https://github.com/matthewdeanmartin/troml_dev_status/issues/
Author: Gemini, ChatGPT
Author-email: Matthew Dean Martin <matthewdeanmartin@gmail.com>
License-File: LICENSE
Keywords: development status,python packaging,trove classifiers
Classifier: Development Status :: 5 - Production/Stable
Classifier: Environment :: Console
Classifier: Framework :: Pydantic
Classifier: Intended Audience :: Developers
Classifier: License :: OSI Approved :: MIT License
Classifier: Programming Language :: Python
Classifier: Programming Language :: Python :: 3.9
Classifier: Programming Language :: Python :: 3.10
Classifier: Programming Language :: Python :: 3.11
Classifier: Programming Language :: Python :: 3.12
Classifier: Programming Language :: Python :: 3.13
Classifier: Programming Language :: Python :: 3.14
Classifier: Topic :: Security
Classifier: Topic :: Software Development
Classifier: Topic :: Software Development :: Build Tools
Classifier: Topic :: Software Development :: Documentation
Classifier: Topic :: Software Development :: Quality Assurance
Classifier: Topic :: Software Development :: Testing
Classifier: Topic :: Utilities
Requires-Python: >=3.9
Requires-Dist: httpx[http2]>=0.28.1
Requires-Dist: jinja2>=3.1.6
Requires-Dist: llvm-diagnostics>=3.0.1
Requires-Dist: packaging>=25.0
Requires-Dist: pathspec>=0.12.1
Requires-Dist: pydantic>=2.11.9
Requires-Dist: pytest>0.0.0
Requires-Dist: pyyaml>=6.0.2
Requires-Dist: rich>=14.1.0
Requires-Dist: semantic-version>=2.10.0
Requires-Dist: textstat>=0.7.10
Requires-Dist: tomli>1.0.0; python_version < '3.11'
Requires-Dist: tomlkit>=0.13.3
